asyncio_toolkit/__init__.py
asyncio_toolkit/version.py
asyncio_toolkit/circuit_breaker/__init__.py
asyncio_toolkit/circuit_breaker/async_await.py
asyncio_toolkit/circuit_breaker/base.py
asyncio_toolkit/circuit_breaker/context_manager.py
asyncio_toolkit/circuit_breaker/coroutine.py
asyncio_toolkit/circuit_breaker/storage.py
luizalabs_asyncio_toolkit-0.2.3.dist-info/DESCRIPTION.rst
luizalabs_asyncio_toolkit-0.2.3.dist-info/METADATA
luizalabs_asyncio_toolkit-0.2.3.dist-info/RECORD
luizalabs_asyncio_toolkit-0.2.3.dist-info/WHEEL
luizalabs_asyncio_toolkit-0.2.3.dist-info/metadata.json
luizalabs_asyncio_toolkit-0.2.3.dist-info/pbr.json
luizalabs_asyncio_toolkit-0.2.3.dist-info/top_level.txt
